HISTORY.txt
README.txt
TODO.txt
bootstrap.py
buildout.cfg
setup.py
ely/__init__.py
ely.croppableimagefield.egg-info/PKG-INFO
ely.croppableimagefield.egg-info/SOURCES.txt
ely.croppableimagefield.egg-info/dependency_links.txt
ely.croppableimagefield.egg-info/namespace_packages.txt
ely.croppableimagefield.egg-info/not-zip-safe
ely.croppableimagefield.egg-info/requires.txt
ely.croppableimagefield.egg-info/top_level.txt
ely/croppableimagefield/README.txt
ely/croppableimagefield/__init__.py
ely/croppableimagefield/croppableimagefield.py
ely/croppableimagefield/tests/__init__.py
ely/croppableimagefield/tests/tests.py
ely/croppableimagefield/tests/input/IMG_0001.jpg
ely/croppableimagefield/tests/input/IMG_0002.jpg