Metadata-Version: 1.0
Name: ely.croppableimagefield
Version: 1.0b1
Summary: CroppableImageField is a drop-in replacement for the Archetype field ImageField
Home-page: http://pypi.python.org/pypi/ely.croppableimagefield
Author: Michael Dunstan
Author-email: michael@elyt.com
License: GPL
Platform: UNKNOWN
Classifier: Framework :: Plone
Classifier: License :: OSI Approved :: GNU General Public License (GPL)
